azureml/__init__.py
azureml/contrib/__init__.py
azureml/contrib/core/__init__.py
azureml/contrib/core/_cli.py
azureml/contrib/core/compute/__init__.py
azureml/contrib/core/compute/_util.py
azureml/contrib/core/compute/iothub.py
azureml/contrib/core/compute/data/iothub_compute_template.json
azureml/contrib/core/webservice/__init__.py
azureml/contrib/core/webservice/_util.py
azureml/contrib/core/webservice/iot.py
azureml/contrib/core/webservice/data/iot_service_payload_template.json
azureml/contrib/iot/__init__.py
azureml/contrib/iot/_cli.py
azureml/contrib/iot/_container_image_request_builder.py
azureml/contrib/iot/iot_image.py
azureml/contrib/iot/model_converters/__init__.py
azureml/contrib/iot/model_converters/snpe_converter.py
azureml_contrib_iot-1.60.0.dist-info/licenses/LICENSE.txt
azureml_contrib_iot-1.60.0.dist-info/METADATA
azureml_contrib_iot-1.60.0.dist-info/WHEEL
azureml_contrib_iot-1.60.0.dist-info/top_level.txt
azureml_contrib_iot-1.60.0.dist-info/RECORD
